MANIFEST.in
pyproject.toml
setup.cfg
setup.py
in_image_blend/__init__.py
in_image_blend/image_blend.c
in_image_blend/image_blend.pyx
in_image_blend.egg-info/PKG-INFO
in_image_blend.egg-info/SOURCES.txt
in_image_blend.egg-info/dependency_links.txt
in_image_blend.egg-info/requires.txt
in_image_blend.egg-info/top_level.txt