Metadata-Version: 2.4
Name: in_image_blend
Version: 0.1.4
Author: in_xs
Classifier: Programming Language :: Python :: 3
Classifier: Programming Language :: Cython
Classifier: Operating System :: OS Independent
Requires-Python: >=3.6
Requires-Dist: numpy
Requires-Dist: Cython
Dynamic: author
Dynamic: classifier
Dynamic: requires-dist
Dynamic: requires-python
